vlbi_cat_creation/__init__.py
vlbi_cat_creation/__main__.py
vlbi_cat_creation/cli.py
vlbi_cat_creation/create_bdsf_cat.py
vlbi_cat_creation-0.1.1.dist-info/METADATA
vlbi_cat_creation-0.1.1.dist-info/WHEEL
vlbi_cat_creation-0.1.1.dist-info/entry_points.txt
vlbi_cat_creation-0.1.1.dist-info/RECORD
