Metadata-Version: 2.4
Name: vlbi-cat-creation
Version: 0.1.1
Summary: Create master catalogues from radio images
Requires-Python: >=3.12
Requires-Dist: argparse>=1.4.0
Requires-Dist: bdsf[ishell]>=1.13.0.post2
Requires-Dist: pathlib>=1.0.1
